{
  "tickets": [
    {
      "id": 1,
      "title": "Example: Fix Authentication Bug",
      "description": "Users cannot login with @ symbol. Review auth validation logic and provide fix. Check /src/auth/validator.js line 45.",
      "priority": "high",
      "status": "reported",
      "tags": [
        "BUG",
        "AUTH",
        "BACKEND"
      ],
      "created": "2025-09-24T15:53:38.095Z",
      "files": [
        "src/auth/validator.js"
      ],
      "workflowId": "workflow-1"
    },
    {
      "id": 2,
      "title": "Improve health of Backend API (currently 47%)",
      "description": "Improve health of Backend API (currently 47%)\nRelated modules: backend\nThis ticket was generated automatically during the latest Opnix audit. Review spec/docs exports for full context.",
      "priority": "high",
      "status": "reported",
      "tags": [
        "FOLLOW_UP",
        "AUDIT"
      ],
      "modules": [
        "backend"
      ],
      "created": "2025-09-25T16:17:36.261Z",
      "source": "audit-follow-up",
      "workflowId": "workflow-2"
    },
    {
      "id": 3,
      "title": "Increase automated test coverage for Backend API (currently 0%)",
      "description": "Increase automated test coverage for Backend API (currently 0%)\nRelated modules: backend\nThis ticket was generated automatically during the latest Opnix audit. Review spec/docs exports for full context.",
      "priority": "high",
      "status": "reported",
      "tags": [
        "FOLLOW_UP",
        "AUDIT"
      ],
      "modules": [
        "backend"
      ],
      "created": "2025-09-25T16:17:36.261Z",
      "source": "audit-follow-up"
    },
    {
      "id": 4,
      "title": "Backend API contains 5 TODO/FIXME markers that need attention",
      "description": "Backend API contains 5 TODO/FIXME markers that need attention\nRelated modules: backend\nThis ticket was generated automatically during the latest Opnix audit. Review spec/docs exports for full context.",
      "priority": "high",
      "status": "reported",
      "tags": [
        "FOLLOW_UP",
        "AUDIT"
      ],
      "modules": [
        "backend"
      ],
      "created": "2025-09-25T16:17:36.261Z",
      "source": "audit-follow-up"
    },
    {
      "id": 5,
      "title": "Increase automated test coverage for Agent Library (currently 0%)",
      "description": "Increase automated test coverage for Agent Library (currently 0%)\nRelated modules: agents\nThis ticket was generated automatically during the latest Opnix audit. Review spec/docs exports for full context.",
      "priority": "high",
      "status": "reported",
      "tags": [
        "FOLLOW_UP",
        "AUDIT"
      ],
      "modules": [
        "agents"
      ],
      "created": "2025-09-25T16:17:36.261Z",
      "source": "audit-follow-up"
    },
    {
      "id": 6,
      "title": "Increase automated test coverage for Workspace Data (currently 0%)",
      "description": "Increase automated test coverage for Workspace Data (currently 0%)\nRelated modules: data\nThis ticket was generated automatically during the latest Opnix audit. Review spec/docs exports for full context.",
      "priority": "high",
      "status": "reported",
      "tags": [
        "FOLLOW_UP",
        "AUDIT"
      ],
      "modules": [
        "data"
      ],
      "created": "2025-09-25T16:17:36.261Z",
      "source": "audit-follow-up"
    },
    {
      "id": 7,
      "title": "Increase automated test coverage for Documentation (currently 0%)",
      "description": "Increase automated test coverage for Documentation (currently 0%)\nRelated modules: docs\nThis ticket was generated automatically during the latest Opnix audit. Review spec/docs exports for full context.",
      "priority": "high",
      "status": "reported",
      "tags": [
        "FOLLOW_UP",
        "AUDIT"
      ],
      "modules": [
        "docs"
      ],
      "created": "2025-09-25T16:17:36.261Z",
      "source": "audit-follow-up"
    },
    {
      "id": 8,
      "title": "Increase automated test coverage for Frontend Interface (currently 33%)",
      "description": "Increase automated test coverage for Frontend Interface (currently 33%)\nRelated modules: frontend\nThis ticket was generated automatically during the latest Opnix audit. Review spec/docs exports for full context.",
      "priority": "high",
      "status": "reported",
      "tags": [
        "FOLLOW_UP",
        "AUDIT"
      ],
      "modules": [
        "frontend"
      ],
      "created": "2025-09-25T16:17:36.261Z",
      "source": "audit-follow-up"
    },
    {
      "id": 9,
      "title": "Frontend Interface contains 4 TODO/FIXME markers that need attention",
      "description": "Frontend Interface contains 4 TODO/FIXME markers that need attention\nRelated modules: frontend\nThis ticket was generated automatically during the latest Opnix audit. Review spec/docs exports for full context.",
      "priority": "high",
      "status": "reported",
      "tags": [
        "FOLLOW_UP",
        "AUDIT"
      ],
      "modules": [
        "frontend"
      ],
      "created": "2025-09-25T16:17:36.261Z",
      "source": "audit-follow-up"
    },
    {
      "id": 10,
      "title": "Increase automated test coverage for Automation Scripts (currently 33%)",
      "description": "Increase automated test coverage for Automation Scripts (currently 33%)\nRelated modules: scripts\nThis ticket was generated automatically during the latest Opnix audit. Review spec/docs exports for full context.",
      "priority": "high",
      "status": "reported",
      "tags": [
        "FOLLOW_UP",
        "AUDIT"
      ],
      "modules": [
        "scripts"
      ],
      "created": "2025-09-25T16:17:36.261Z",
      "source": "audit-follow-up"
    },
    {
      "id": 11,
      "title": "Improve health of Services (currently 20%)",
      "description": "Improve health of Services (currently 20%)\nRelated modules: services\nThis ticket was generated automatically during the latest Opnix audit. Review spec/docs exports for full context.",
      "priority": "high",
      "status": "reported",
      "tags": [
        "FOLLOW_UP",
        "AUDIT"
      ],
      "modules": [
        "services"
      ],
      "created": "2025-09-25T16:17:36.261Z",
      "source": "audit-follow-up"
    },
    {
      "id": 12,
      "title": "Increase automated test coverage for Services (currently 14%)",
      "description": "Increase automated test coverage for Services (currently 14%)\nRelated modules: services\nThis ticket was generated automatically during the latest Opnix audit. Review spec/docs exports for full context.",
      "priority": "high",
      "status": "reported",
      "tags": [
        "FOLLOW_UP",
        "AUDIT"
      ],
      "modules": [
        "services"
      ],
      "created": "2025-09-25T16:17:36.261Z",
      "source": "audit-follow-up"
    },
    {
      "id": 13,
      "title": "Services contains 30 TODO/FIXME markers that need attention",
      "description": "Services contains 30 TODO/FIXME markers that need attention\nRelated modules: services\nThis ticket was generated automatically during the latest Opnix audit. Review spec/docs exports for full context.",
      "priority": "high",
      "status": "reported",
      "tags": [
        "FOLLOW_UP",
        "AUDIT"
      ],
      "modules": [
        "services"
      ],
      "created": "2025-09-25T16:17:36.261Z",
      "source": "audit-follow-up"
    },
    {
      "id": 14,
      "title": "Improve health of Spec Archive (currently 20%)",
      "description": "Improve health of Spec Archive (currently 20%)\nRelated modules: spec\nThis ticket was generated automatically during the latest Opnix audit. Review spec/docs exports for full context.",
      "priority": "high",
      "status": "reported",
      "tags": [
        "FOLLOW_UP",
        "AUDIT"
      ],
      "modules": [
        "spec"
      ],
      "created": "2025-09-25T16:17:36.261Z",
      "source": "audit-follow-up"
    },
    {
      "id": 15,
      "title": "Spec Archive contains 50 TODO/FIXME markers that need attention",
      "description": "Spec Archive contains 50 TODO/FIXME markers that need attention\nRelated modules: spec\nThis ticket was generated automatically during the latest Opnix audit. Review spec/docs exports for full context.",
      "priority": "high",
      "status": "reported",
      "tags": [
        "FOLLOW_UP",
        "AUDIT"
      ],
      "modules": [
        "spec"
      ],
      "created": "2025-09-25T16:17:36.261Z",
      "source": "audit-follow-up"
    },
    {
      "id": 16,
      "title": "Increase automated test coverage for Application Source (currently 38%)",
      "description": "Increase automated test coverage for Application Source (currently 38%)\nRelated modules: src\nThis ticket was generated automatically during the latest Opnix audit. Review spec/docs exports for full context.",
      "priority": "high",
      "status": "reported",
      "tags": [
        "FOLLOW_UP",
        "AUDIT"
      ],
      "modules": [
        "src"
      ],
      "created": "2025-09-25T16:17:36.261Z",
      "source": "audit-follow-up"
    },
    {
      "id": 17,
      "title": "Application Source contains 1 TODO/FIXME markers that need attention",
      "description": "Application Source contains 1 TODO/FIXME markers that need attention\nRelated modules: src\nThis ticket was generated automatically during the latest Opnix audit. Review spec/docs exports for full context.",
      "priority": "high",
      "status": "reported",
      "tags": [
        "FOLLOW_UP",
        "AUDIT"
      ],
      "modules": [
        "src"
      ],
      "created": "2025-09-25T16:17:36.261Z",
      "source": "audit-follow-up"
    },
    {
      "id": 18,
      "title": "Resolve 1 open high-priority ticket",
      "description": "Resolve 1 open high-priority ticket\nThis ticket was generated automatically during the latest Opnix audit. Review spec/docs exports for full context.",
      "priority": "high",
      "status": "reported",
      "tags": [
        "FOLLOW_UP",
        "AUDIT"
      ],
      "modules": [],
      "created": "2025-09-25T16:17:36.261Z",
      "source": "audit-follow-up"
    },
    {
      "id": 19,
      "title": "Improve health of Workspace Data (currently 20%)",
      "description": "Improve health of Workspace Data (currently 20%)\nRelated modules: data\nThis ticket was generated automatically during the latest Opnix audit. Review spec/docs exports for full context.",
      "priority": "high",
      "status": "reported",
      "tags": [
        "FOLLOW_UP",
        "AUDIT"
      ],
      "modules": [
        "data"
      ],
      "created": "2025-09-27T13:27:01.541Z",
      "source": "audit-follow-up"
    },
    {
      "id": 20,
      "title": "Workspace Data contains 43 TODO/FIXME markers that need attention",
      "description": "Workspace Data contains 43 TODO/FIXME markers that need attention\nRelated modules: data\nThis ticket was generated automatically during the latest Opnix audit. Review spec/docs exports for full context.",
      "priority": "high",
      "status": "reported",
      "tags": [
        "FOLLOW_UP",
        "AUDIT"
      ],
      "modules": [
        "data"
      ],
      "created": "2025-09-27T13:27:01.541Z",
      "source": "audit-follow-up"
    },
    {
      "id": 21,
      "title": "Improve health of Legacy Exports (currently 20%)",
      "description": "Improve health of Legacy Exports (currently 20%)\nRelated modules: legacy-exports\nThis ticket was generated automatically during the latest Opnix audit. Review spec/docs exports for full context.",
      "priority": "high",
      "status": "reported",
      "tags": [
        "FOLLOW_UP",
        "AUDIT"
      ],
      "modules": [
        "legacy-exports"
      ],
      "created": "2025-09-27T13:27:01.541Z",
      "source": "audit-follow-up"
    },
    {
      "id": 22,
      "title": "Increase automated test coverage for Legacy Exports (currently 0%)",
      "description": "Increase automated test coverage for Legacy Exports (currently 0%)\nRelated modules: legacy-exports\nThis ticket was generated automatically during the latest Opnix audit. Review spec/docs exports for full context.",
      "priority": "high",
      "status": "reported",
      "tags": [
        "FOLLOW_UP",
        "AUDIT"
      ],
      "modules": [
        "legacy-exports"
      ],
      "created": "2025-09-27T13:27:01.541Z",
      "source": "audit-follow-up"
    },
    {
      "id": 23,
      "title": "Legacy Exports contains 30 TODO/FIXME markers that need attention",
      "description": "Legacy Exports contains 30 TODO/FIXME markers that need attention\nRelated modules: legacy-exports\nThis ticket was generated automatically during the latest Opnix audit. Review spec/docs exports for full context.",
      "priority": "high",
      "status": "reported",
      "tags": [
        "FOLLOW_UP",
        "AUDIT"
      ],
      "modules": [
        "legacy-exports"
      ],
      "created": "2025-09-27T13:27:01.541Z",
      "source": "audit-follow-up"
    },
    {
      "id": 24,
      "title": "Improve health of Frontend Interface (currently 35%)",
      "description": "Improve health of Frontend Interface (currently 35%)\nRelated modules: frontend\nThis ticket was generated automatically during the latest Opnix audit. Review spec/docs exports for full context.",
      "priority": "high",
      "status": "reported",
      "tags": [
        "FOLLOW_UP",
        "AUDIT"
      ],
      "modules": [
        "frontend"
      ],
      "created": "2025-09-27T13:27:01.541Z",
      "source": "audit-follow-up"
    },
    {
      "id": 25,
      "title": "Increase automated test coverage for Frontend Interface (currently 0%)",
      "description": "Increase automated test coverage for Frontend Interface (currently 0%)\nRelated modules: frontend\nThis ticket was generated automatically during the latest Opnix audit. Review spec/docs exports for full context.",
      "priority": "high",
      "status": "reported",
      "tags": [
        "FOLLOW_UP",
        "AUDIT"
      ],
      "modules": [
        "frontend"
      ],
      "created": "2025-09-27T13:27:01.541Z",
      "source": "audit-follow-up"
    },
    {
      "id": 26,
      "title": "Frontend Interface contains 8 TODO/FIXME markers that need attention",
      "description": "Frontend Interface contains 8 TODO/FIXME markers that need attention\nRelated modules: frontend\nThis ticket was generated automatically during the latest Opnix audit. Review spec/docs exports for full context.",
      "priority": "high",
      "status": "reported",
      "tags": [
        "FOLLOW_UP",
        "AUDIT"
      ],
      "modules": [
        "frontend"
      ],
      "created": "2025-09-27T13:27:01.541Z",
      "source": "audit-follow-up"
    },
    {
      "id": 27,
      "title": "Increase automated test coverage for Routes (currently 6%)",
      "description": "Increase automated test coverage for Routes (currently 6%)\nRelated modules: routes\nThis ticket was generated automatically during the latest Opnix audit. Review spec/docs exports for full context.",
      "priority": "high",
      "status": "reported",
      "tags": [
        "FOLLOW_UP",
        "AUDIT"
      ],
      "modules": [
        "routes"
      ],
      "created": "2025-09-27T13:27:01.541Z",
      "source": "audit-follow-up"
    },
    {
      "id": 28,
      "title": "Increase automated test coverage for Automation Scripts (currently 20%)",
      "description": "Increase automated test coverage for Automation Scripts (currently 20%)\nRelated modules: scripts\nThis ticket was generated automatically during the latest Opnix audit. Review spec/docs exports for full context.",
      "priority": "high",
      "status": "reported",
      "tags": [
        "FOLLOW_UP",
        "AUDIT"
      ],
      "modules": [
        "scripts"
      ],
      "created": "2025-09-27T13:27:01.541Z",
      "source": "audit-follow-up"
    },
    {
      "id": 29,
      "title": "Increase automated test coverage for Services (currently 11%)",
      "description": "Increase automated test coverage for Services (currently 11%)\nRelated modules: services\nThis ticket was generated automatically during the latest Opnix audit. Review spec/docs exports for full context.",
      "priority": "high",
      "status": "reported",
      "tags": [
        "FOLLOW_UP",
        "AUDIT"
      ],
      "modules": [
        "services"
      ],
      "created": "2025-09-27T13:27:01.541Z",
      "source": "audit-follow-up"
    },
    {
      "id": 30,
      "title": "Services contains 48 TODO/FIXME markers that need attention",
      "description": "Services contains 48 TODO/FIXME markers that need attention\nRelated modules: services\nThis ticket was generated automatically during the latest Opnix audit. Review spec/docs exports for full context.",
      "priority": "high",
      "status": "reported",
      "tags": [
        "FOLLOW_UP",
        "AUDIT"
      ],
      "modules": [
        "services"
      ],
      "created": "2025-09-27T13:27:01.541Z",
      "source": "audit-follow-up"
    },
    {
      "id": 31,
      "title": "Spec Archive contains 122 TODO/FIXME markers that need attention",
      "description": "Spec Archive contains 122 TODO/FIXME markers that need attention\nRelated modules: spec\nThis ticket was generated automatically during the latest Opnix audit. Review spec/docs exports for full context.",
      "priority": "high",
      "status": "reported",
      "tags": [
        "FOLLOW_UP",
        "AUDIT"
      ],
      "modules": [
        "spec"
      ],
      "created": "2025-09-27T13:27:01.541Z",
      "source": "audit-follow-up"
    },
    {
      "id": 32,
      "title": "Increase automated test coverage for Application Source (currently 10%)",
      "description": "Increase automated test coverage for Application Source (currently 10%)\nRelated modules: src\nThis ticket was generated automatically during the latest Opnix audit. Review spec/docs exports for full context.",
      "priority": "high",
      "status": "reported",
      "tags": [
        "FOLLOW_UP",
        "AUDIT"
      ],
      "modules": [
        "src"
      ],
      "created": "2025-09-27T13:27:01.541Z",
      "source": "audit-follow-up"
    },
    {
      "id": 33,
      "title": "Resolve 18 open high-priority tickets",
      "description": "Resolve 18 open high-priority tickets\nThis ticket was generated automatically during the latest Opnix audit. Review spec/docs exports for full context.",
      "priority": "high",
      "status": "reported",
      "tags": [
        "FOLLOW_UP",
        "AUDIT"
      ],
      "modules": [],
      "created": "2025-09-27T13:27:01.541Z",
      "source": "audit-follow-up"
    },
    {
      "id": 34,
      "title": "Workspace Data contains 64 TODO/FIXME markers that need attention",
      "description": "Workspace Data contains 64 TODO/FIXME markers that need attention\nRelated modules: data\nThis ticket was generated automatically during the latest Opnix audit. Review spec/docs exports for full context.",
      "priority": "high",
      "status": "reported",
      "tags": [
        "FOLLOW_UP",
        "AUDIT"
      ],
      "modules": [
        "data"
      ],
      "created": "2025-09-27T14:03:01.836Z",
      "source": "audit-follow-up"
    },
    {
      "id": 35,
      "title": "Spec Archive contains 187 TODO/FIXME markers that need attention",
      "description": "Spec Archive contains 187 TODO/FIXME markers that need attention\nRelated modules: spec\nThis ticket was generated automatically during the latest Opnix audit. Review spec/docs exports for full context.",
      "priority": "high",
      "status": "reported",
      "tags": [
        "FOLLOW_UP",
        "AUDIT"
      ],
      "modules": [
        "spec"
      ],
      "created": "2025-09-27T14:03:01.836Z",
      "source": "audit-follow-up"
    },
    {
      "id": 36,
      "title": "Improve health of Storybook Static (currently 20%)",
      "description": "Improve health of Storybook Static (currently 20%)\nRelated modules: storybook-static\nThis ticket was generated automatically during the latest Opnix audit. Review spec/docs exports for full context.",
      "priority": "high",
      "status": "reported",
      "tags": [
        "FOLLOW_UP",
        "AUDIT"
      ],
      "modules": [
        "storybook-static"
      ],
      "created": "2025-09-27T14:03:01.836Z",
      "source": "audit-follow-up"
    },
    {
      "id": 37,
      "title": "Increase automated test coverage for Storybook Static (currently 0%)",
      "description": "Increase automated test coverage for Storybook Static (currently 0%)\nRelated modules: storybook-static\nThis ticket was generated automatically during the latest Opnix audit. Review spec/docs exports for full context.",
      "priority": "high",
      "status": "reported",
      "tags": [
        "FOLLOW_UP",
        "AUDIT"
      ],
      "modules": [
        "storybook-static"
      ],
      "created": "2025-09-27T14:03:01.836Z",
      "source": "audit-follow-up"
    },
    {
      "id": 38,
      "title": "Storybook Static contains 56 TODO/FIXME markers that need attention",
      "description": "Storybook Static contains 56 TODO/FIXME markers that need attention\nRelated modules: storybook-static\nThis ticket was generated automatically during the latest Opnix audit. Review spec/docs exports for full context.",
      "priority": "high",
      "status": "reported",
      "tags": [
        "FOLLOW_UP",
        "AUDIT"
      ],
      "modules": [
        "storybook-static"
      ],
      "created": "2025-09-27T14:03:01.836Z",
      "source": "audit-follow-up"
    },
    {
      "id": 39,
      "title": "Resolve 33 open high-priority tickets",
      "description": "Resolve 33 open high-priority tickets\nThis ticket was generated automatically during the latest Opnix audit. Review spec/docs exports for full context.",
      "priority": "high",
      "status": "reported",
      "tags": [
        "FOLLOW_UP",
        "AUDIT"
      ],
      "modules": [],
      "created": "2025-09-27T14:03:01.836Z",
      "source": "audit-follow-up"
    },
    {
      "id": 40,
      "title": "Workspace Data contains 76 TODO/FIXME markers that need attention",
      "description": "Workspace Data contains 76 TODO/FIXME markers that need attention\nRelated modules: data\nThis ticket was generated automatically during the latest Opnix audit. Review spec/docs exports for full context.",
      "priority": "high",
      "status": "reported",
      "tags": [
        "FOLLOW_UP",
        "AUDIT"
      ],
      "modules": [
        "data"
      ],
      "created": "2025-09-27T14:03:36.277Z",
      "source": "audit-follow-up"
    },
    {
      "id": 41,
      "title": "Spec Archive contains 272 TODO/FIXME markers that need attention",
      "description": "Spec Archive contains 272 TODO/FIXME markers that need attention\nRelated modules: spec\nThis ticket was generated automatically during the latest Opnix audit. Review spec/docs exports for full context.",
      "priority": "high",
      "status": "reported",
      "tags": [
        "FOLLOW_UP",
        "AUDIT"
      ],
      "modules": [
        "spec"
      ],
      "created": "2025-09-27T14:03:36.277Z",
      "source": "audit-follow-up"
    },
    {
      "id": 42,
      "title": "Resolve 39 open high-priority tickets",
      "description": "Resolve 39 open high-priority tickets\nThis ticket was generated automatically during the latest Opnix audit. Review spec/docs exports for full context.",
      "priority": "high",
      "status": "reported",
      "tags": [
        "FOLLOW_UP",
        "AUDIT"
      ],
      "modules": [],
      "created": "2025-09-27T14:03:36.277Z",
      "source": "audit-follow-up"
    },
    {
      "id": 43,
      "title": "Workspace Data contains 84 TODO/FIXME markers that need attention",
      "description": "Workspace Data contains 84 TODO/FIXME markers that need attention\nRelated modules: data\nThis ticket was generated automatically during the latest Opnix audit. Review spec/docs exports for full context.",
      "priority": "high",
      "status": "reported",
      "tags": [
        "FOLLOW_UP",
        "AUDIT"
      ],
      "modules": [
        "data"
      ],
      "created": "2025-09-27T14:08:32.680Z",
      "source": "audit-follow-up"
    },
    {
      "id": 44,
      "title": "Spec Archive contains 367 TODO/FIXME markers that need attention",
      "description": "Spec Archive contains 367 TODO/FIXME markers that need attention\nRelated modules: spec\nThis ticket was generated automatically during the latest Opnix audit. Review spec/docs exports for full context.",
      "priority": "high",
      "status": "reported",
      "tags": [
        "FOLLOW_UP",
        "AUDIT"
      ],
      "modules": [
        "spec"
      ],
      "created": "2025-09-27T14:08:32.680Z",
      "source": "audit-follow-up"
    },
    {
      "id": 45,
      "title": "Increase automated test coverage for Application Source (currently 9%)",
      "description": "Increase automated test coverage for Application Source (currently 9%)\nRelated modules: src\nThis ticket was generated automatically during the latest Opnix audit. Review spec/docs exports for full context.",
      "priority": "high",
      "status": "reported",
      "tags": [
        "FOLLOW_UP",
        "AUDIT"
      ],
      "modules": [
        "src"
      ],
      "created": "2025-09-27T14:08:32.680Z",
      "source": "audit-follow-up"
    },
    {
      "id": 46,
      "title": "Resolve 42 open high-priority tickets",
      "description": "Resolve 42 open high-priority tickets\nThis ticket was generated automatically during the latest Opnix audit. Review spec/docs exports for full context.",
      "priority": "high",
      "status": "reported",
      "tags": [
        "FOLLOW_UP",
        "AUDIT"
      ],
      "modules": [],
      "created": "2025-09-27T14:08:32.680Z",
      "source": "audit-follow-up"
    },
    {
      "id": 47,
      "title": "Workspace Data contains 92 TODO/FIXME markers that need attention",
      "description": "Workspace Data contains 92 TODO/FIXME markers that need attention\nRelated modules: data\nThis ticket was generated automatically during the latest Opnix audit. Review spec/docs exports for full context.",
      "priority": "high",
      "status": "reported",
      "tags": [
        "FOLLOW_UP",
        "AUDIT"
      ],
      "modules": [
        "data"
      ],
      "created": "2025-09-27T15:11:03.839Z",
      "source": "audit-follow-up"
    },
    {
      "id": 48,
      "title": "Spec Archive contains 470 TODO/FIXME markers that need attention",
      "description": "Spec Archive contains 470 TODO/FIXME markers that need attention\nRelated modules: spec\nThis ticket was generated automatically during the latest Opnix audit. Review spec/docs exports for full context.",
      "priority": "high",
      "status": "reported",
      "tags": [
        "FOLLOW_UP",
        "AUDIT"
      ],
      "modules": [
        "spec"
      ],
      "created": "2025-09-27T15:11:03.839Z",
      "source": "audit-follow-up"
    },
    {
      "id": 49,
      "title": "Resolve 46 open high-priority tickets",
      "description": "Resolve 46 open high-priority tickets\nThis ticket was generated automatically during the latest Opnix audit. Review spec/docs exports for full context.",
      "priority": "high",
      "status": "reported",
      "tags": [
        "FOLLOW_UP",
        "AUDIT"
      ],
      "modules": [],
      "created": "2025-09-27T15:11:03.839Z",
      "source": "audit-follow-up"
    },
    {
      "id": 50,
      "title": "Workspace Data contains 100 TODO/FIXME markers that need attention",
      "description": "Workspace Data contains 100 TODO/FIXME markers that need attention\nRelated modules: data\nThis ticket was generated automatically during the latest Opnix audit. Review spec/docs exports for full context.",
      "priority": "high",
      "status": "reported",
      "tags": [
        "FOLLOW_UP",
        "AUDIT"
      ],
      "modules": [
        "data"
      ],
      "created": "2025-09-27T15:23:52.605Z",
      "source": "audit-follow-up"
    },
    {
      "id": 51,
      "title": "Spec Archive contains 581 TODO/FIXME markers that need attention",
      "description": "Spec Archive contains 581 TODO/FIXME markers that need attention\nRelated modules: spec\nThis ticket was generated automatically during the latest Opnix audit. Review spec/docs exports for full context.",
      "priority": "high",
      "status": "reported",
      "tags": [
        "FOLLOW_UP",
        "AUDIT"
      ],
      "modules": [
        "spec"
      ],
      "created": "2025-09-27T15:23:52.605Z",
      "source": "audit-follow-up"
    },
    {
      "id": 52,
      "title": "Increase automated test coverage for Application Source (currently 8%)",
      "description": "Increase automated test coverage for Application Source (currently 8%)\nRelated modules: src\nThis ticket was generated automatically during the latest Opnix audit. Review spec/docs exports for full context.",
      "priority": "high",
      "status": "reported",
      "tags": [
        "FOLLOW_UP",
        "AUDIT"
      ],
      "modules": [
        "src"
      ],
      "created": "2025-09-27T15:23:52.605Z",
      "source": "audit-follow-up"
    },
    {
      "id": 53,
      "title": "Resolve 49 open high-priority tickets",
      "description": "Resolve 49 open high-priority tickets\nThis ticket was generated automatically during the latest Opnix audit. Review spec/docs exports for full context.",
      "priority": "high",
      "status": "reported",
      "tags": [
        "FOLLOW_UP",
        "AUDIT"
      ],
      "modules": [],
      "created": "2025-09-27T15:23:52.605Z",
      "source": "audit-follow-up"
    },
    {
      "id": 54,
      "title": "Workspace Data contains 108 TODO/FIXME markers that need attention",
      "description": "Workspace Data contains 108 TODO/FIXME markers that need attention\nRelated modules: data\nThis ticket was generated automatically during the latest Opnix audit. Review spec/docs exports for full context.",
      "priority": "high",
      "status": "reported",
      "tags": [
        "FOLLOW_UP",
        "AUDIT"
      ],
      "modules": [
        "data"
      ],
      "created": "2025-09-27T15:43:44.319Z",
      "source": "audit-follow-up"
    },
    {
      "id": 55,
      "title": "Spec Archive contains 700 TODO/FIXME markers that need attention",
      "description": "Spec Archive contains 700 TODO/FIXME markers that need attention\nRelated modules: spec\nThis ticket was generated automatically during the latest Opnix audit. Review spec/docs exports for full context.",
      "priority": "high",
      "status": "reported",
      "tags": [
        "FOLLOW_UP",
        "AUDIT"
      ],
      "modules": [
        "spec"
      ],
      "created": "2025-09-27T15:43:44.319Z",
      "source": "audit-follow-up"
    },
    {
      "id": 56,
      "title": "Increase automated test coverage for Application Source (currently 7%)",
      "description": "Increase automated test coverage for Application Source (currently 7%)\nRelated modules: src\nThis ticket was generated automatically during the latest Opnix audit. Review spec/docs exports for full context.",
      "priority": "high",
      "status": "reported",
      "tags": [
        "FOLLOW_UP",
        "AUDIT"
      ],
      "modules": [
        "src"
      ],
      "created": "2025-09-27T15:43:44.319Z",
      "source": "audit-follow-up"
    },
    {
      "id": 57,
      "title": "Resolve 53 open high-priority tickets",
      "description": "Resolve 53 open high-priority tickets\nThis ticket was generated automatically during the latest Opnix audit. Review spec/docs exports for full context.",
      "priority": "high",
      "status": "reported",
      "tags": [
        "FOLLOW_UP",
        "AUDIT"
      ],
      "modules": [],
      "created": "2025-09-27T15:43:44.319Z",
      "source": "audit-follow-up"
    },
    {
      "id": 58,
      "title": "Workspace Data contains 116 TODO/FIXME markers that need attention",
      "description": "Workspace Data contains 116 TODO/FIXME markers that need attention\nRelated modules: data\nThis ticket was generated automatically during the latest Opnix audit. Review spec/docs exports for full context.",
      "priority": "high",
      "status": "reported",
      "tags": [
        "FOLLOW_UP",
        "AUDIT"
      ],
      "modules": [
        "data"
      ],
      "created": "2025-09-27T16:05:39.842Z",
      "source": "audit-follow-up"
    },
    {
      "id": 59,
      "title": "Spec Archive contains 827 TODO/FIXME markers that need attention",
      "description": "Spec Archive contains 827 TODO/FIXME markers that need attention\nRelated modules: spec\nThis ticket was generated automatically during the latest Opnix audit. Review spec/docs exports for full context.",
      "priority": "high",
      "status": "reported",
      "tags": [
        "FOLLOW_UP",
        "AUDIT"
      ],
      "modules": [
        "spec"
      ],
      "created": "2025-09-27T16:05:39.842Z",
      "source": "audit-follow-up"
    },
    {
      "id": 60,
      "title": "Resolve 57 open high-priority tickets",
      "description": "Resolve 57 open high-priority tickets\nThis ticket was generated automatically during the latest Opnix audit. Review spec/docs exports for full context.",
      "priority": "high",
      "status": "reported",
      "tags": [
        "FOLLOW_UP",
        "AUDIT"
      ],
      "modules": [],
      "created": "2025-09-27T16:05:39.842Z",
      "source": "audit-follow-up"
    },
    {
      "id": 61,
      "title": "Workspace Data contains 124 TODO/FIXME markers that need attention",
      "description": "Workspace Data contains 124 TODO/FIXME markers that need attention\nRelated modules: data\nThis ticket was generated automatically during the latest Opnix audit. Review spec/docs exports for full context.",
      "priority": "high",
      "status": "reported",
      "tags": [
        "FOLLOW_UP",
        "AUDIT"
      ],
      "modules": [
        "data"
      ],
      "created": "2025-09-27T16:28:56.929Z",
      "source": "audit-follow-up"
    },
    {
      "id": 62,
      "title": "Spec Archive contains 962 TODO/FIXME markers that need attention",
      "description": "Spec Archive contains 962 TODO/FIXME markers that need attention\nRelated modules: spec\nThis ticket was generated automatically during the latest Opnix audit. Review spec/docs exports for full context.",
      "priority": "high",
      "status": "reported",
      "tags": [
        "FOLLOW_UP",
        "AUDIT"
      ],
      "modules": [
        "spec"
      ],
      "created": "2025-09-27T16:28:56.929Z",
      "source": "audit-follow-up"
    },
    {
      "id": 63,
      "title": "Resolve 60 open high-priority tickets",
      "description": "Resolve 60 open high-priority tickets\nThis ticket was generated automatically during the latest Opnix audit. Review spec/docs exports for full context.",
      "priority": "high",
      "status": "reported",
      "tags": [
        "FOLLOW_UP",
        "AUDIT"
      ],
      "modules": [],
      "created": "2025-09-27T16:28:56.929Z",
      "source": "audit-follow-up"
    },
    {
      "id": 64,
      "title": "Workspace Data contains 132 TODO/FIXME markers that need attention",
      "description": "Workspace Data contains 132 TODO/FIXME markers that need attention\nRelated modules: data\nThis ticket was generated automatically during the latest Opnix audit. Review spec/docs exports for full context.",
      "priority": "high",
      "status": "reported",
      "tags": [
        "FOLLOW_UP",
        "AUDIT"
      ],
      "modules": [
        "data"
      ],
      "created": "2025-09-27T17:08:38.773Z",
      "source": "audit-follow-up"
    },
    {
      "id": 65,
      "title": "Spec Archive contains 1105 TODO/FIXME markers that need attention",
      "description": "Spec Archive contains 1105 TODO/FIXME markers that need attention\nRelated modules: spec\nThis ticket was generated automatically during the latest Opnix audit. Review spec/docs exports for full context.",
      "priority": "high",
      "status": "reported",
      "tags": [
        "FOLLOW_UP",
        "AUDIT"
      ],
      "modules": [
        "spec"
      ],
      "created": "2025-09-27T17:08:38.773Z",
      "source": "audit-follow-up"
    },
    {
      "id": 66,
      "title": "Resolve 63 open high-priority tickets",
      "description": "Resolve 63 open high-priority tickets\nThis ticket was generated automatically during the latest Opnix audit. Review spec/docs exports for full context.",
      "priority": "high",
      "status": "reported",
      "tags": [
        "FOLLOW_UP",
        "AUDIT"
      ],
      "modules": [],
      "created": "2025-09-27T17:08:38.773Z",
      "source": "audit-follow-up"
    },
    {
      "id": 67,
      "title": "Workspace Data contains 140 TODO/FIXME markers that need attention",
      "description": "Workspace Data contains 140 TODO/FIXME markers that need attention\nRelated modules: data\nThis ticket was generated automatically during the latest Opnix audit. Review spec/docs exports for full context.",
      "priority": "high",
      "status": "reported",
      "tags": [
        "FOLLOW_UP",
        "AUDIT"
      ],
      "modules": [
        "data"
      ],
      "created": "2025-09-27T17:22:38.359Z",
      "source": "audit-follow-up"
    },
    {
      "id": 68,
      "title": "Spec Archive contains 1256 TODO/FIXME markers that need attention",
      "description": "Spec Archive contains 1256 TODO/FIXME markers that need attention\nRelated modules: spec\nThis ticket was generated automatically during the latest Opnix audit. Review spec/docs exports for full context.",
      "priority": "high",
      "status": "reported",
      "tags": [
        "FOLLOW_UP",
        "AUDIT"
      ],
      "modules": [
        "spec"
      ],
      "created": "2025-09-27T17:22:38.359Z",
      "source": "audit-follow-up"
    },
    {
      "id": 69,
      "title": "Resolve 66 open high-priority tickets",
      "description": "Resolve 66 open high-priority tickets\nThis ticket was generated automatically during the latest Opnix audit. Review spec/docs exports for full context.",
      "priority": "high",
      "status": "reported",
      "tags": [
        "FOLLOW_UP",
        "AUDIT"
      ],
      "modules": [],
      "created": "2025-09-27T17:22:38.359Z",
      "source": "audit-follow-up"
    },
    {
      "id": 70,
      "title": "Workspace Data contains 148 TODO/FIXME markers that need attention",
      "description": "Workspace Data contains 148 TODO/FIXME markers that need attention\nRelated modules: data\nThis ticket was generated automatically during the latest Opnix audit. Review spec/docs exports for full context.",
      "priority": "high",
      "status": "reported",
      "tags": [
        "FOLLOW_UP",
        "AUDIT"
      ],
      "modules": [
        "data"
      ],
      "created": "2025-09-27T17:23:43.930Z",
      "source": "audit-follow-up"
    },
    {
      "id": 71,
      "title": "Spec Archive contains 1415 TODO/FIXME markers that need attention",
      "description": "Spec Archive contains 1415 TODO/FIXME markers that need attention\nRelated modules: spec\nThis ticket was generated automatically during the latest Opnix audit. Review spec/docs exports for full context.",
      "priority": "high",
      "status": "reported",
      "tags": [
        "FOLLOW_UP",
        "AUDIT"
      ],
      "modules": [
        "spec"
      ],
      "created": "2025-09-27T17:23:43.930Z",
      "source": "audit-follow-up"
    },
    {
      "id": 72,
      "title": "Resolve 69 open high-priority tickets",
      "description": "Resolve 69 open high-priority tickets\nThis ticket was generated automatically during the latest Opnix audit. Review spec/docs exports for full context.",
      "priority": "high",
      "status": "reported",
      "tags": [
        "FOLLOW_UP",
        "AUDIT"
      ],
      "modules": [],
      "created": "2025-09-27T17:23:43.930Z",
      "source": "audit-follow-up"
    },
    {
      "id": 73,
      "title": "Workspace Data contains 156 TODO/FIXME markers that need attention",
      "description": "Workspace Data contains 156 TODO/FIXME markers that need attention\nRelated modules: data\nThis ticket was generated automatically during the latest Opnix audit. Review spec/docs exports for full context.",
      "priority": "high",
      "status": "reported",
      "tags": [
        "FOLLOW_UP",
        "AUDIT"
      ],
      "modules": [
        "data"
      ],
      "created": "2025-09-27T17:29:19.243Z",
      "source": "audit-follow-up"
    },
    {
      "id": 74,
      "title": "Spec Archive contains 1582 TODO/FIXME markers that need attention",
      "description": "Spec Archive contains 1582 TODO/FIXME markers that need attention\nRelated modules: spec\nThis ticket was generated automatically during the latest Opnix audit. Review spec/docs exports for full context.",
      "priority": "high",
      "status": "reported",
      "tags": [
        "FOLLOW_UP",
        "AUDIT"
      ],
      "modules": [
        "spec"
      ],
      "created": "2025-09-27T17:29:19.243Z",
      "source": "audit-follow-up"
    },
    {
      "id": 75,
      "title": "Resolve 72 open high-priority tickets",
      "description": "Resolve 72 open high-priority tickets\nThis ticket was generated automatically during the latest Opnix audit. Review spec/docs exports for full context.",
      "priority": "high",
      "status": "reported",
      "tags": [
        "FOLLOW_UP",
        "AUDIT"
      ],
      "modules": [],
      "created": "2025-09-27T17:29:19.243Z",
      "source": "audit-follow-up"
    },
    {
      "id": 76,
      "title": "Workspace Data contains 164 TODO/FIXME markers that need attention",
      "description": "Workspace Data contains 164 TODO/FIXME markers that need attention\nRelated modules: data\nThis ticket was generated automatically during the latest Opnix audit. Review spec/docs exports for full context.",
      "priority": "high",
      "status": "reported",
      "tags": [
        "FOLLOW_UP",
        "AUDIT"
      ],
      "modules": [
        "data"
      ],
      "created": "2025-09-27T19:10:37.474Z",
      "source": "audit-follow-up"
    },
    {
      "id": 77,
      "title": "Spec Archive contains 1757 TODO/FIXME markers that need attention",
      "description": "Spec Archive contains 1757 TODO/FIXME markers that need attention\nRelated modules: spec\nThis ticket was generated automatically during the latest Opnix audit. Review spec/docs exports for full context.",
      "priority": "high",
      "status": "reported",
      "tags": [
        "FOLLOW_UP",
        "AUDIT"
      ],
      "modules": [
        "spec"
      ],
      "created": "2025-09-27T19:10:37.474Z",
      "source": "audit-follow-up"
    },
    {
      "id": 78,
      "title": "Resolve 75 open high-priority tickets",
      "description": "Resolve 75 open high-priority tickets\nThis ticket was generated automatically during the latest Opnix audit. Review spec/docs exports for full context.",
      "priority": "high",
      "status": "reported",
      "tags": [
        "FOLLOW_UP",
        "AUDIT"
      ],
      "modules": [],
      "created": "2025-09-27T19:10:37.474Z",
      "source": "audit-follow-up"
    },
    {
      "id": 79,
      "title": "Workspace Data contains 172 TODO/FIXME markers that need attention",
      "description": "Workspace Data contains 172 TODO/FIXME markers that need attention\nRelated modules: data\nThis ticket was generated automatically during the latest Opnix audit. Review spec/docs exports for full context.",
      "priority": "high",
      "status": "reported",
      "tags": [
        "FOLLOW_UP",
        "AUDIT"
      ],
      "modules": [
        "data"
      ],
      "created": "2025-09-27T19:21:39.893Z",
      "source": "audit-follow-up"
    },
    {
      "id": 80,
      "title": "Spec Archive contains 1940 TODO/FIXME markers that need attention",
      "description": "Spec Archive contains 1940 TODO/FIXME markers that need attention\nRelated modules: spec\nThis ticket was generated automatically during the latest Opnix audit. Review spec/docs exports for full context.",
      "priority": "high",
      "status": "reported",
      "tags": [
        "FOLLOW_UP",
        "AUDIT"
      ],
      "modules": [
        "spec"
      ],
      "created": "2025-09-27T19:21:39.893Z",
      "source": "audit-follow-up"
    },
    {
      "id": 81,
      "title": "Resolve 78 open high-priority tickets",
      "description": "Resolve 78 open high-priority tickets\nThis ticket was generated automatically during the latest Opnix audit. Review spec/docs exports for full context.",
      "priority": "high",
      "status": "reported",
      "tags": [
        "FOLLOW_UP",
        "AUDIT"
      ],
      "modules": [],
      "created": "2025-09-27T19:21:39.893Z",
      "source": "audit-follow-up"
    },
    {
      "id": 82,
      "title": "Workspace Data contains 180 TODO/FIXME markers that need attention",
      "description": "Workspace Data contains 180 TODO/FIXME markers that need attention\nRelated modules: data\nThis ticket was generated automatically during the latest Opnix audit. Review spec/docs exports for full context.",
      "priority": "high",
      "status": "reported",
      "tags": [
        "FOLLOW_UP",
        "AUDIT"
      ],
      "modules": [
        "data"
      ],
      "created": "2025-09-27T19:29:50.486Z",
      "source": "audit-follow-up"
    },
    {
      "id": 83,
      "title": "Spec Archive contains 2131 TODO/FIXME markers that need attention",
      "description": "Spec Archive contains 2131 TODO/FIXME markers that need attention\nRelated modules: spec\nThis ticket was generated automatically during the latest Opnix audit. Review spec/docs exports for full context.",
      "priority": "high",
      "status": "reported",
      "tags": [
        "FOLLOW_UP",
        "AUDIT"
      ],
      "modules": [
        "spec"
      ],
      "created": "2025-09-27T19:29:50.486Z",
      "source": "audit-follow-up"
    },
    {
      "id": 84,
      "title": "Resolve 81 open high-priority tickets",
      "description": "Resolve 81 open high-priority tickets\nThis ticket was generated automatically during the latest Opnix audit. Review spec/docs exports for full context.",
      "priority": "high",
      "status": "reported",
      "tags": [
        "FOLLOW_UP",
        "AUDIT"
      ],
      "modules": [],
      "created": "2025-09-27T19:29:50.486Z",
      "source": "audit-follow-up"
    },
    {
      "id": 85,
      "title": "Workspace Data contains 188 TODO/FIXME markers that need attention",
      "description": "Workspace Data contains 188 TODO/FIXME markers that need attention\nRelated modules: data\nThis ticket was generated automatically during the latest Opnix audit. Review spec/docs exports for full context.",
      "priority": "high",
      "status": "reported",
      "tags": [
        "FOLLOW_UP",
        "AUDIT"
      ],
      "modules": [
        "data"
      ],
      "created": "2025-09-27T19:40:37.037Z",
      "source": "audit-follow-up"
    },
    {
      "id": 86,
      "title": "Spec Archive contains 2330 TODO/FIXME markers that need attention",
      "description": "Spec Archive contains 2330 TODO/FIXME markers that need attention\nRelated modules: spec\nThis ticket was generated automatically during the latest Opnix audit. Review spec/docs exports for full context.",
      "priority": "high",
      "status": "reported",
      "tags": [
        "FOLLOW_UP",
        "AUDIT"
      ],
      "modules": [
        "spec"
      ],
      "created": "2025-09-27T19:40:37.037Z",
      "source": "audit-follow-up"
    },
    {
      "id": 87,
      "title": "Resolve 84 open high-priority tickets",
      "description": "Resolve 84 open high-priority tickets\nThis ticket was generated automatically during the latest Opnix audit. Review spec/docs exports for full context.",
      "priority": "high",
      "status": "reported",
      "tags": [
        "FOLLOW_UP",
        "AUDIT"
      ],
      "modules": [],
      "created": "2025-09-27T19:40:37.037Z",
      "source": "audit-follow-up"
    },
    {
      "id": 88,
      "title": "Workspace Data contains 196 TODO/FIXME markers that need attention",
      "description": "Workspace Data contains 196 TODO/FIXME markers that need attention\nRelated modules: data\nThis ticket was generated automatically during the latest Opnix audit. Review spec/docs exports for full context.",
      "priority": "high",
      "status": "reported",
      "tags": [
        "FOLLOW_UP",
        "AUDIT"
      ],
      "modules": [
        "data"
      ],
      "created": "2025-09-27T20:08:24.186Z",
      "source": "audit-follow-up"
    },
    {
      "id": 89,
      "title": "Spec Archive contains 2537 TODO/FIXME markers that need attention",
      "description": "Spec Archive contains 2537 TODO/FIXME markers that need attention\nRelated modules: spec\nThis ticket was generated automatically during the latest Opnix audit. Review spec/docs exports for full context.",
      "priority": "high",
      "status": "reported",
      "tags": [
        "FOLLOW_UP",
        "AUDIT"
      ],
      "modules": [
        "spec"
      ],
      "created": "2025-09-27T20:08:24.186Z",
      "source": "audit-follow-up"
    },
    {
      "id": 90,
      "title": "Resolve 87 open high-priority tickets",
      "description": "Resolve 87 open high-priority tickets\nThis ticket was generated automatically during the latest Opnix audit. Review spec/docs exports for full context.",
      "priority": "high",
      "status": "reported",
      "tags": [
        "FOLLOW_UP",
        "AUDIT"
      ],
      "modules": [],
      "created": "2025-09-27T20:08:24.186Z",
      "source": "audit-follow-up"
    },
    {
      "id": 91,
      "title": "Workspace Data contains 204 TODO/FIXME markers that need attention",
      "description": "Workspace Data contains 204 TODO/FIXME markers that need attention\nRelated modules: data\nThis ticket was generated automatically during the latest Opnix audit. Review spec/docs exports for full context.",
      "priority": "high",
      "status": "reported",
      "tags": [
        "FOLLOW_UP",
        "AUDIT"
      ],
      "modules": [
        "data"
      ],
      "created": "2025-09-27T20:11:36.025Z",
      "source": "audit-follow-up"
    },
    {
      "id": 92,
      "title": "Spec Archive contains 2752 TODO/FIXME markers that need attention",
      "description": "Spec Archive contains 2752 TODO/FIXME markers that need attention\nRelated modules: spec\nThis ticket was generated automatically during the latest Opnix audit. Review spec/docs exports for full context.",
      "priority": "high",
      "status": "reported",
      "tags": [
        "FOLLOW_UP",
        "AUDIT"
      ],
      "modules": [
        "spec"
      ],
      "created": "2025-09-27T20:11:36.025Z",
      "source": "audit-follow-up"
    },
    {
      "id": 93,
      "title": "Resolve 90 open high-priority tickets",
      "description": "Resolve 90 open high-priority tickets\nThis ticket was generated automatically during the latest Opnix audit. Review spec/docs exports for full context.",
      "priority": "high",
      "status": "reported",
      "tags": [
        "FOLLOW_UP",
        "AUDIT"
      ],
      "modules": [],
      "created": "2025-09-27T20:11:36.025Z",
      "source": "audit-follow-up"
    },
    {
      "id": 94,
      "title": "Workspace Data contains 212 TODO/FIXME markers that need attention",
      "description": "Workspace Data contains 212 TODO/FIXME markers that need attention\nRelated modules: data\nThis ticket was generated automatically during the latest Opnix audit. Review spec/docs exports for full context.",
      "priority": "high",
      "status": "reported",
      "tags": [
        "FOLLOW_UP",
        "AUDIT"
      ],
      "modules": [
        "data"
      ],
      "created": "2025-09-27T20:14:13.563Z",
      "source": "audit-follow-up"
    },
    {
      "id": 95,
      "title": "Spec Archive contains 2975 TODO/FIXME markers that need attention",
      "description": "Spec Archive contains 2975 TODO/FIXME markers that need attention\nRelated modules: spec\nThis ticket was generated automatically during the latest Opnix audit. Review spec/docs exports for full context.",
      "priority": "high",
      "status": "reported",
      "tags": [
        "FOLLOW_UP",
        "AUDIT"
      ],
      "modules": [
        "spec"
      ],
      "created": "2025-09-27T20:14:13.563Z",
      "source": "audit-follow-up"
    },
    {
      "id": 96,
      "title": "Resolve 93 open high-priority tickets",
      "description": "Resolve 93 open high-priority tickets\nThis ticket was generated automatically during the latest Opnix audit. Review spec/docs exports for full context.",
      "priority": "high",
      "status": "reported",
      "tags": [
        "FOLLOW_UP",
        "AUDIT"
      ],
      "modules": [],
      "created": "2025-09-27T20:14:13.563Z",
      "source": "audit-follow-up"
    },
    {
      "id": 97,
      "title": "Workspace Data contains 220 TODO/FIXME markers that need attention",
      "description": "Workspace Data contains 220 TODO/FIXME markers that need attention\nRelated modules: data\nThis ticket was generated automatically during the latest Opnix audit. Review spec/docs exports for full context.",
      "priority": "high",
      "status": "reported",
      "tags": [
        "FOLLOW_UP",
        "AUDIT"
      ],
      "modules": [
        "data"
      ],
      "created": "2025-09-27T20:38:36.090Z",
      "source": "audit-follow-up"
    },
    {
      "id": 98,
      "title": "Spec Archive contains 3206 TODO/FIXME markers that need attention",
      "description": "Spec Archive contains 3206 TODO/FIXME markers that need attention\nRelated modules: spec\nThis ticket was generated automatically during the latest Opnix audit. Review spec/docs exports for full context.",
      "priority": "high",
      "status": "reported",
      "tags": [
        "FOLLOW_UP",
        "AUDIT"
      ],
      "modules": [
        "spec"
      ],
      "created": "2025-09-27T20:38:36.090Z",
      "source": "audit-follow-up"
    },
    {
      "id": 99,
      "title": "Resolve 96 open high-priority tickets",
      "description": "Resolve 96 open high-priority tickets\nThis ticket was generated automatically during the latest Opnix audit. Review spec/docs exports for full context.",
      "priority": "high",
      "status": "reported",
      "tags": [
        "FOLLOW_UP",
        "AUDIT"
      ],
      "modules": [],
      "created": "2025-09-27T20:38:36.090Z",
      "source": "audit-follow-up"
    },
    {
      "id": 100,
      "title": "Workspace Data contains 228 TODO/FIXME markers that need attention",
      "description": "Workspace Data contains 228 TODO/FIXME markers that need attention\nRelated modules: data\nThis ticket was generated automatically during the latest Opnix audit. Review spec/docs exports for full context.",
      "priority": "high",
      "status": "reported",
      "tags": [
        "FOLLOW_UP",
        "AUDIT"
      ],
      "modules": [
        "data"
      ],
      "created": "2025-09-27T20:38:52.778Z",
      "source": "audit-follow-up"
    },
    {
      "id": 101,
      "title": "Spec Archive contains 3445 TODO/FIXME markers that need attention",
      "description": "Spec Archive contains 3445 TODO/FIXME markers that need attention\nRelated modules: spec\nThis ticket was generated automatically during the latest Opnix audit. Review spec/docs exports for full context.",
      "priority": "high",
      "status": "reported",
      "tags": [
        "FOLLOW_UP",
        "AUDIT"
      ],
      "modules": [
        "spec"
      ],
      "created": "2025-09-27T20:38:52.778Z",
      "source": "audit-follow-up"
    },
    {
      "id": 102,
      "title": "Resolve 99 open high-priority tickets",
      "description": "Resolve 99 open high-priority tickets\nThis ticket was generated automatically during the latest Opnix audit. Review spec/docs exports for full context.",
      "priority": "high",
      "status": "reported",
      "tags": [
        "FOLLOW_UP",
        "AUDIT"
      ],
      "modules": [],
      "created": "2025-09-27T20:38:52.778Z",
      "source": "audit-follow-up"
    },
    {
      "id": 103,
      "title": "Workspace Data contains 236 TODO/FIXME markers that need attention",
      "description": "Workspace Data contains 236 TODO/FIXME markers that need attention\nRelated modules: data\nThis ticket was generated automatically during the latest Opnix audit. Review spec/docs exports for full context.",
      "priority": "high",
      "status": "reported",
      "tags": [
        "FOLLOW_UP",
        "AUDIT"
      ],
      "modules": [
        "data"
      ],
      "created": "2025-09-27T20:48:35.656Z",
      "source": "audit-follow-up"
    },
    {
      "id": 104,
      "title": "Spec Archive contains 3692 TODO/FIXME markers that need attention",
      "description": "Spec Archive contains 3692 TODO/FIXME markers that need attention\nRelated modules: spec\nThis ticket was generated automatically during the latest Opnix audit. Review spec/docs exports for full context.",
      "priority": "high",
      "status": "reported",
      "tags": [
        "FOLLOW_UP",
        "AUDIT"
      ],
      "modules": [
        "spec"
      ],
      "created": "2025-09-27T20:48:35.656Z",
      "source": "audit-follow-up"
    },
    {
      "id": 105,
      "title": "Resolve 102 open high-priority tickets",
      "description": "Resolve 102 open high-priority tickets\nThis ticket was generated automatically during the latest Opnix audit. Review spec/docs exports for full context.",
      "priority": "high",
      "status": "reported",
      "tags": [
        "FOLLOW_UP",
        "AUDIT"
      ],
      "modules": [],
      "created": "2025-09-27T20:48:35.656Z",
      "source": "audit-follow-up"
    },
    {
      "id": 106,
      "title": "Workspace Data contains 244 TODO/FIXME markers that need attention",
      "description": "Workspace Data contains 244 TODO/FIXME markers that need attention\nRelated modules: data\nThis ticket was generated automatically during the latest Opnix audit. Review spec/docs exports for full context.",
      "priority": "high",
      "status": "reported",
      "tags": [
        "FOLLOW_UP",
        "AUDIT"
      ],
      "modules": [
        "data"
      ],
      "created": "2025-09-27T20:51:05.692Z",
      "source": "audit-follow-up"
    },
    {
      "id": 107,
      "title": "Spec Archive contains 3947 TODO/FIXME markers that need attention",
      "description": "Spec Archive contains 3947 TODO/FIXME markers that need attention\nRelated modules: spec\nThis ticket was generated automatically during the latest Opnix audit. Review spec/docs exports for full context.",
      "priority": "high",
      "status": "reported",
      "tags": [
        "FOLLOW_UP",
        "AUDIT"
      ],
      "modules": [
        "spec"
      ],
      "created": "2025-09-27T20:51:05.692Z",
      "source": "audit-follow-up"
    },
    {
      "id": 108,
      "title": "Resolve 105 open high-priority tickets",
      "description": "Resolve 105 open high-priority tickets\nThis ticket was generated automatically during the latest Opnix audit. Review spec/docs exports for full context.",
      "priority": "high",
      "status": "reported",
      "tags": [
        "FOLLOW_UP",
        "AUDIT"
      ],
      "modules": [],
      "created": "2025-09-27T20:51:05.692Z",
      "source": "audit-follow-up"
    },
    {
      "id": 109,
      "title": "Workspace Data contains 252 TODO/FIXME markers that need attention",
      "description": "Workspace Data contains 252 TODO/FIXME markers that need attention\nRelated modules: data\nThis ticket was generated automatically during the latest Opnix audit. Review spec/docs exports for full context.",
      "priority": "high",
      "status": "reported",
      "tags": [
        "FOLLOW_UP",
        "AUDIT"
      ],
      "modules": [
        "data"
      ],
      "created": "2025-09-27T20:54:29.863Z",
      "source": "audit-follow-up"
    },
    {
      "id": 110,
      "title": "Spec Archive contains 4210 TODO/FIXME markers that need attention",
      "description": "Spec Archive contains 4210 TODO/FIXME markers that need attention\nRelated modules: spec\nThis ticket was generated automatically during the latest Opnix audit. Review spec/docs exports for full context.",
      "priority": "high",
      "status": "reported",
      "tags": [
        "FOLLOW_UP",
        "AUDIT"
      ],
      "modules": [
        "spec"
      ],
      "created": "2025-09-27T20:54:29.863Z",
      "source": "audit-follow-up"
    },
    {
      "id": 111,
      "title": "Resolve 108 open high-priority tickets",
      "description": "Resolve 108 open high-priority tickets\nThis ticket was generated automatically during the latest Opnix audit. Review spec/docs exports for full context.",
      "priority": "high",
      "status": "reported",
      "tags": [
        "FOLLOW_UP",
        "AUDIT"
      ],
      "modules": [],
      "created": "2025-09-27T20:54:29.863Z",
      "source": "audit-follow-up"
    },
    {
      "id": 112,
      "title": "Workspace Data contains 260 TODO/FIXME markers that need attention",
      "description": "Workspace Data contains 260 TODO/FIXME markers that need attention\nRelated modules: data\nThis ticket was generated automatically during the latest Opnix audit. Review spec/docs exports for full context.",
      "priority": "high",
      "status": "reported",
      "tags": [
        "FOLLOW_UP",
        "AUDIT"
      ],
      "modules": [
        "data"
      ],
      "created": "2025-09-27T21:03:05.561Z",
      "source": "audit-follow-up"
    },
    {
      "id": 113,
      "title": "Spec Archive contains 4481 TODO/FIXME markers that need attention",
      "description": "Spec Archive contains 4481 TODO/FIXME markers that need attention\nRelated modules: spec\nThis ticket was generated automatically during the latest Opnix audit. Review spec/docs exports for full context.",
      "priority": "high",
      "status": "reported",
      "tags": [
        "FOLLOW_UP",
        "AUDIT"
      ],
      "modules": [
        "spec"
      ],
      "created": "2025-09-27T21:03:05.561Z",
      "source": "audit-follow-up"
    },
    {
      "id": 114,
      "title": "Resolve 111 open high-priority tickets",
      "description": "Resolve 111 open high-priority tickets\nThis ticket was generated automatically during the latest Opnix audit. Review spec/docs exports for full context.",
      "priority": "high",
      "status": "reported",
      "tags": [
        "FOLLOW_UP",
        "AUDIT"
      ],
      "modules": [],
      "created": "2025-09-27T21:03:05.561Z",
      "source": "audit-follow-up"
    },
    {
      "id": 115,
      "title": "Workspace Data contains 268 TODO/FIXME markers that need attention",
      "description": "Workspace Data contains 268 TODO/FIXME markers that need attention\nRelated modules: data\nThis ticket was generated automatically during the latest Opnix audit. Review spec/docs exports for full context.",
      "priority": "high",
      "status": "reported",
      "tags": [
        "FOLLOW_UP",
        "AUDIT"
      ],
      "modules": [
        "data"
      ],
      "created": "2025-09-27T21:21:38.705Z",
      "source": "audit-follow-up"
    },
    {
      "id": 116,
      "title": "Spec Archive contains 4760 TODO/FIXME markers that need attention",
      "description": "Spec Archive contains 4760 TODO/FIXME markers that need attention\nRelated modules: spec\nThis ticket was generated automatically during the latest Opnix audit. Review spec/docs exports for full context.",
      "priority": "high",
      "status": "reported",
      "tags": [
        "FOLLOW_UP",
        "AUDIT"
      ],
      "modules": [
        "spec"
      ],
      "created": "2025-09-27T21:21:38.705Z",
      "source": "audit-follow-up"
    },
    {
      "id": 117,
      "title": "Resolve 114 open high-priority tickets",
      "description": "Resolve 114 open high-priority tickets\nThis ticket was generated automatically during the latest Opnix audit. Review spec/docs exports for full context.",
      "priority": "high",
      "status": "reported",
      "tags": [
        "FOLLOW_UP",
        "AUDIT"
      ],
      "modules": [],
      "created": "2025-09-27T21:21:38.705Z",
      "source": "audit-follow-up"
    },
    {
      "id": 118,
      "title": "Workspace Data contains 276 TODO/FIXME markers that need attention",
      "description": "Workspace Data contains 276 TODO/FIXME markers that need attention\nRelated modules: data\nThis ticket was generated automatically during the latest Opnix audit. Review spec/docs exports for full context.",
      "priority": "high",
      "status": "reported",
      "tags": [
        "FOLLOW_UP",
        "AUDIT"
      ],
      "modules": [
        "data"
      ],
      "created": "2025-09-27T21:28:35.315Z",
      "source": "audit-follow-up"
    },
    {
      "id": 119,
      "title": "Increase automated test coverage for Services (currently 10%)",
      "description": "Increase automated test coverage for Services (currently 10%)\nRelated modules: services\nThis ticket was generated automatically during the latest Opnix audit. Review spec/docs exports for full context.",
      "priority": "high",
      "status": "reported",
      "tags": [
        "FOLLOW_UP",
        "AUDIT"
      ],
      "modules": [
        "services"
      ],
      "created": "2025-09-27T21:28:35.315Z",
      "source": "audit-follow-up"
    },
    {
      "id": 120,
      "title": "Spec Archive contains 5047 TODO/FIXME markers that need attention",
      "description": "Spec Archive contains 5047 TODO/FIXME markers that need attention\nRelated modules: spec\nThis ticket was generated automatically during the latest Opnix audit. Review spec/docs exports for full context.",
      "priority": "high",
      "status": "reported",
      "tags": [
        "FOLLOW_UP",
        "AUDIT"
      ],
      "modules": [
        "spec"
      ],
      "created": "2025-09-27T21:28:35.315Z",
      "source": "audit-follow-up"
    },
    {
      "id": 121,
      "title": "Resolve 117 open high-priority tickets",
      "description": "Resolve 117 open high-priority tickets\nThis ticket was generated automatically during the latest Opnix audit. Review spec/docs exports for full context.",
      "priority": "high",
      "status": "reported",
      "tags": [
        "FOLLOW_UP",
        "AUDIT"
      ],
      "modules": [],
      "created": "2025-09-27T21:28:35.315Z",
      "source": "audit-follow-up"
    },
    {
      "id": 122,
      "title": "Workspace Data contains 284 TODO/FIXME markers that need attention",
      "description": "Workspace Data contains 284 TODO/FIXME markers that need attention\nRelated modules: data\nThis ticket was generated automatically during the latest Opnix audit. Review spec/docs exports for full context.",
      "priority": "high",
      "status": "reported",
      "tags": [
        "FOLLOW_UP",
        "AUDIT"
      ],
      "modules": [
        "data"
      ],
      "created": "2025-09-27T22:03:12.368Z",
      "source": "audit-follow-up"
    },
    {
      "id": 123,
      "title": "Spec Archive contains 5342 TODO/FIXME markers that need attention",
      "description": "Spec Archive contains 5342 TODO/FIXME markers that need attention\nRelated modules: spec\nThis ticket was generated automatically during the latest Opnix audit. Review spec/docs exports for full context.",
      "priority": "high",
      "status": "reported",
      "tags": [
        "FOLLOW_UP",
        "AUDIT"
      ],
      "modules": [
        "spec"
      ],
      "created": "2025-09-27T22:03:12.368Z",
      "source": "audit-follow-up"
    },
    {
      "id": 124,
      "title": "Resolve 121 open high-priority tickets",
      "description": "Resolve 121 open high-priority tickets\nThis ticket was generated automatically during the latest Opnix audit. Review spec/docs exports for full context.",
      "priority": "high",
      "status": "reported",
      "tags": [
        "FOLLOW_UP",
        "AUDIT"
      ],
      "modules": [],
      "created": "2025-09-27T22:03:12.368Z",
      "source": "audit-follow-up"
    },
    {
      "id": 125,
      "title": "Workspace Data contains 292 TODO/FIXME markers that need attention",
      "description": "Workspace Data contains 292 TODO/FIXME markers that need attention\nRelated modules: data\nThis ticket was generated automatically during the latest Opnix audit. Review spec/docs exports for full context.",
      "priority": "high",
      "status": "reported",
      "tags": [
        "FOLLOW_UP",
        "AUDIT"
      ],
      "modules": [
        "data"
      ],
      "created": "2025-09-27T22:11:43.524Z",
      "source": "audit-follow-up"
    },
    {
      "id": 126,
      "title": "Spec Archive contains 5645 TODO/FIXME markers that need attention",
      "description": "Spec Archive contains 5645 TODO/FIXME markers that need attention\nRelated modules: spec\nThis ticket was generated automatically during the latest Opnix audit. Review spec/docs exports for full context.",
      "priority": "high",
      "status": "reported",
      "tags": [
        "FOLLOW_UP",
        "AUDIT"
      ],
      "modules": [
        "spec"
      ],
      "created": "2025-09-27T22:11:43.524Z",
      "source": "audit-follow-up"
    },
    {
      "id": 127,
      "title": "Resolve 124 open high-priority tickets",
      "description": "Resolve 124 open high-priority tickets\nThis ticket was generated automatically during the latest Opnix audit. Review spec/docs exports for full context.",
      "priority": "high",
      "status": "reported",
      "tags": [
        "FOLLOW_UP",
        "AUDIT"
      ],
      "modules": [],
      "created": "2025-09-27T22:11:43.524Z",
      "source": "audit-follow-up"
    },
    {
      "id": 128,
      "title": "Workspace Data contains 301 TODO/FIXME markers that need attention",
      "description": "Workspace Data contains 301 TODO/FIXME markers that need attention\nRelated modules: data\nThis ticket was generated automatically during the latest Opnix audit. Review spec/docs exports for full context.",
      "priority": "high",
      "status": "reported",
      "tags": [
        "FOLLOW_UP",
        "AUDIT"
      ],
      "modules": [
        "data"
      ],
      "created": "2025-09-28T09:20:36.941Z",
      "source": "audit-follow-up"
    },
    {
      "id": 129,
      "title": "Legacy Exports contains 50 TODO/FIXME markers that need attention",
      "description": "Legacy Exports contains 50 TODO/FIXME markers that need attention\nRelated modules: legacy-exports\nThis ticket was generated automatically during the latest Opnix audit. Review spec/docs exports for full context.",
      "priority": "high",
      "status": "reported",
      "tags": [
        "FOLLOW_UP",
        "AUDIT"
      ],
      "modules": [
        "legacy-exports"
      ],
      "created": "2025-09-28T09:20:36.941Z",
      "source": "audit-follow-up"
    },
    {
      "id": 130,
      "title": "Increase automated test coverage for Automation Scripts (currently 17%)",
      "description": "Increase automated test coverage for Automation Scripts (currently 17%)\nRelated modules: scripts\nThis ticket was generated automatically during the latest Opnix audit. Review spec/docs exports for full context.",
      "priority": "high",
      "status": "reported",
      "tags": [
        "FOLLOW_UP",
        "AUDIT"
      ],
      "modules": [
        "scripts"
      ],
      "created": "2025-09-28T09:20:36.941Z",
      "source": "audit-follow-up"
    },
    {
      "id": 131,
      "title": "Automation Scripts contains 3 TODO/FIXME markers that need attention",
      "description": "Automation Scripts contains 3 TODO/FIXME markers that need attention\nRelated modules: scripts\nThis ticket was generated automatically during the latest Opnix audit. Review spec/docs exports for full context.",
      "priority": "high",
      "status": "reported",
      "tags": [
        "FOLLOW_UP",
        "AUDIT"
      ],
      "modules": [
        "scripts"
      ],
      "created": "2025-09-28T09:20:36.941Z",
      "source": "audit-follow-up"
    },
    {
      "id": 132,
      "title": "Increase automated test coverage for Services (currently 9%)",
      "description": "Increase automated test coverage for Services (currently 9%)\nRelated modules: services\nThis ticket was generated automatically during the latest Opnix audit. Review spec/docs exports for full context.",
      "priority": "high",
      "status": "reported",
      "tags": [
        "FOLLOW_UP",
        "AUDIT"
      ],
      "modules": [
        "services"
      ],
      "created": "2025-09-28T09:20:36.941Z",
      "source": "audit-follow-up"
    },
    {
      "id": 133,
      "title": "Spec Archive contains 5956 TODO/FIXME markers that need attention",
      "description": "Spec Archive contains 5956 TODO/FIXME markers that need attention\nRelated modules: spec\nThis ticket was generated automatically during the latest Opnix audit. Review spec/docs exports for full context.",
      "priority": "high",
      "status": "reported",
      "tags": [
        "FOLLOW_UP",
        "AUDIT"
      ],
      "modules": [
        "spec"
      ],
      "created": "2025-09-28T09:20:36.941Z",
      "source": "audit-follow-up"
    },
    {
      "id": 134,
      "title": "Increase automated test coverage for Test Output (currently 0%)",
      "description": "Increase automated test coverage for Test Output (currently 0%)\nRelated modules: test-output\nThis ticket was generated automatically during the latest Opnix audit. Review spec/docs exports for full context.",
      "priority": "high",
      "status": "reported",
      "tags": [
        "FOLLOW_UP",
        "AUDIT"
      ],
      "modules": [
        "test-output"
      ],
      "created": "2025-09-28T09:20:36.941Z",
      "source": "audit-follow-up"
    },
    {
      "id": 135,
      "title": "Resolve 127 open high-priority tickets",
      "description": "Resolve 127 open high-priority tickets\nThis ticket was generated automatically during the latest Opnix audit. Review spec/docs exports for full context.",
      "priority": "high",
      "status": "reported",
      "tags": [
        "FOLLOW_UP",
        "AUDIT"
      ],
      "modules": [],
      "created": "2025-09-28T09:20:36.941Z",
      "source": "audit-follow-up"
    },
    {
      "id": 136,
      "title": "Workspace Data contains 317 TODO/FIXME markers that need attention",
      "description": "Workspace Data contains 317 TODO/FIXME markers that need attention\nRelated modules: data\nThis ticket was generated automatically during the latest Opnix audit. Review spec/docs exports for full context.",
      "priority": "high",
      "status": "reported",
      "tags": [
        "FOLLOW_UP",
        "AUDIT"
      ],
      "modules": [
        "data"
      ],
      "created": "2025-09-28T09:54:57.626Z",
      "source": "audit-follow-up"
    },
    {
      "id": 137,
      "title": "Legacy Exports contains 70 TODO/FIXME markers that need attention",
      "description": "Legacy Exports contains 70 TODO/FIXME markers that need attention\nRelated modules: legacy-exports\nThis ticket was generated automatically during the latest Opnix audit. Review spec/docs exports for full context.",
      "priority": "high",
      "status": "reported",
      "tags": [
        "FOLLOW_UP",
        "AUDIT"
      ],
      "modules": [
        "legacy-exports"
      ],
      "created": "2025-09-28T09:54:57.626Z",
      "source": "audit-follow-up"
    },
    {
      "id": 138,
      "title": "Spec Archive contains 6283 TODO/FIXME markers that need attention",
      "description": "Spec Archive contains 6283 TODO/FIXME markers that need attention\nRelated modules: spec\nThis ticket was generated automatically during the latest Opnix audit. Review spec/docs exports for full context.",
      "priority": "high",
      "status": "reported",
      "tags": [
        "FOLLOW_UP",
        "AUDIT"
      ],
      "modules": [
        "spec"
      ],
      "created": "2025-09-28T09:54:57.626Z",
      "source": "audit-follow-up"
    },
    {
      "id": 139,
      "title": "Resolve 135 open high-priority tickets",
      "description": "Resolve 135 open high-priority tickets\nThis ticket was generated automatically during the latest Opnix audit. Review spec/docs exports for full context.",
      "priority": "high",
      "status": "reported",
      "tags": [
        "FOLLOW_UP",
        "AUDIT"
      ],
      "modules": [],
      "created": "2025-09-28T09:54:57.626Z",
      "source": "audit-follow-up"
    },
    {
      "id": 140,
      "title": "Workspace Data contains 330 TODO/FIXME markers that need attention",
      "description": "Workspace Data contains 330 TODO/FIXME markers that need attention\nRelated modules: data\nThis ticket was generated automatically during the latest Opnix audit. Review spec/docs exports for full context.",
      "priority": "high",
      "status": "reported",
      "tags": [
        "FOLLOW_UP",
        "AUDIT"
      ],
      "modules": [
        "data"
      ],
      "created": "2025-09-28T10:06:42.617Z",
      "source": "audit-follow-up"
    },
    {
      "id": 141,
      "title": "Legacy Exports contains 230 TODO/FIXME markers that need attention",
      "description": "Legacy Exports contains 230 TODO/FIXME markers that need attention\nRelated modules: legacy-exports\nThis ticket was generated automatically during the latest Opnix audit. Review spec/docs exports for full context.",
      "priority": "high",
      "status": "reported",
      "tags": [
        "FOLLOW_UP",
        "AUDIT"
      ],
      "modules": [
        "legacy-exports"
      ],
      "created": "2025-09-28T10:06:42.617Z",
      "source": "audit-follow-up"
    },
    {
      "id": 142,
      "title": "Spec Archive contains 6624 TODO/FIXME markers that need attention",
      "description": "Spec Archive contains 6624 TODO/FIXME markers that need attention\nRelated modules: spec\nThis ticket was generated automatically during the latest Opnix audit. Review spec/docs exports for full context.",
      "priority": "high",
      "status": "reported",
      "tags": [
        "FOLLOW_UP",
        "AUDIT"
      ],
      "modules": [
        "spec"
      ],
      "created": "2025-09-28T10:06:42.617Z",
      "source": "audit-follow-up"
    },
    {
      "id": 143,
      "title": "Resolve 139 open high-priority tickets",
      "description": "Resolve 139 open high-priority tickets\nThis ticket was generated automatically during the latest Opnix audit. Review spec/docs exports for full context.",
      "priority": "high",
      "status": "reported",
      "tags": [
        "FOLLOW_UP",
        "AUDIT"
      ],
      "modules": [],
      "created": "2025-09-28T10:06:42.617Z",
      "source": "audit-follow-up"
    },
    {
      "id": 144,
      "title": "Workspace Data contains 344 TODO/FIXME markers that need attention",
      "description": "Workspace Data contains 344 TODO/FIXME markers that need attention\nRelated modules: data\nThis ticket was generated automatically during the latest Opnix audit. Review spec/docs exports for full context.",
      "priority": "high",
      "status": "reported",
      "tags": [
        "FOLLOW_UP",
        "AUDIT"
      ],
      "modules": [
        "data"
      ],
      "created": "2025-09-28T11:22:11.150Z",
      "source": "audit-follow-up"
    },
    {
      "id": 145,
      "title": "Legacy Exports contains 250 TODO/FIXME markers that need attention",
      "description": "Legacy Exports contains 250 TODO/FIXME markers that need attention\nRelated modules: legacy-exports\nThis ticket was generated automatically during the latest Opnix audit. Review spec/docs exports for full context.",
      "priority": "high",
      "status": "reported",
      "tags": [
        "FOLLOW_UP",
        "AUDIT"
      ],
      "modules": [
        "legacy-exports"
      ],
      "created": "2025-09-28T11:22:11.150Z",
      "source": "audit-follow-up"
    },
    {
      "id": 146,
      "title": "Spec Archive contains 6979 TODO/FIXME markers that need attention",
      "description": "Spec Archive contains 6979 TODO/FIXME markers that need attention\nRelated modules: spec\nThis ticket was generated automatically during the latest Opnix audit. Review spec/docs exports for full context.",
      "priority": "high",
      "status": "reported",
      "tags": [
        "FOLLOW_UP",
        "AUDIT"
      ],
      "modules": [
        "spec"
      ],
      "created": "2025-09-28T11:22:11.150Z",
      "source": "audit-follow-up"
    },
    {
      "id": 147,
      "title": "Resolve 143 open high-priority tickets",
      "description": "Resolve 143 open high-priority tickets\nThis ticket was generated automatically during the latest Opnix audit. Review spec/docs exports for full context.",
      "priority": "high",
      "status": "reported",
      "tags": [
        "FOLLOW_UP",
        "AUDIT"
      ],
      "modules": [],
      "created": "2025-09-28T11:22:11.150Z",
      "source": "audit-follow-up"
    },
    {
      "id": 148,
      "title": "Workspace Data contains 356 TODO/FIXME markers that need attention",
      "description": "Workspace Data contains 356 TODO/FIXME markers that need attention\nRelated modules: data\nThis ticket was generated automatically during the latest Opnix audit. Review spec/docs exports for full context.",
      "priority": "high",
      "status": "reported",
      "tags": [
        "FOLLOW_UP",
        "AUDIT"
      ],
      "modules": [
        "data"
      ],
      "created": "2025-09-28T11:53:22.729Z",
      "source": "audit-follow-up"
    },
    {
      "id": 149,
      "title": "Spec Archive contains 7346 TODO/FIXME markers that need attention",
      "description": "Spec Archive contains 7346 TODO/FIXME markers that need attention\nRelated modules: spec\nThis ticket was generated automatically during the latest Opnix audit. Review spec/docs exports for full context.",
      "priority": "high",
      "status": "reported",
      "tags": [
        "FOLLOW_UP",
        "AUDIT"
      ],
      "modules": [
        "spec"
      ],
      "created": "2025-09-28T11:53:22.729Z",
      "source": "audit-follow-up"
    },
    {
      "id": 150,
      "title": "Resolve 147 open high-priority tickets",
      "description": "Resolve 147 open high-priority tickets\nThis ticket was generated automatically during the latest Opnix audit. Review spec/docs exports for full context.",
      "priority": "high",
      "status": "reported",
      "tags": [
        "FOLLOW_UP",
        "AUDIT"
      ],
      "modules": [],
      "created": "2025-09-28T11:53:22.729Z",
      "source": "audit-follow-up"
    },
    {
      "id": 151,
      "title": "Workspace Data contains 364 TODO/FIXME markers that need attention",
      "description": "Workspace Data contains 364 TODO/FIXME markers that need attention\nRelated modules: data\nThis ticket was generated automatically during the latest Opnix audit. Review spec/docs exports for full context.",
      "priority": "high",
      "status": "reported",
      "tags": [
        "FOLLOW_UP",
        "AUDIT"
      ],
      "modules": [
        "data"
      ],
      "created": "2025-09-28T12:31:29.470Z",
      "source": "audit-follow-up"
    },
    {
      "id": 152,
      "title": "Spec Archive contains 7723 TODO/FIXME markers that need attention",
      "description": "Spec Archive contains 7723 TODO/FIXME markers that need attention\nRelated modules: spec\nThis ticket was generated automatically during the latest Opnix audit. Review spec/docs exports for full context.",
      "priority": "high",
      "status": "reported",
      "tags": [
        "FOLLOW_UP",
        "AUDIT"
      ],
      "modules": [
        "spec"
      ],
      "created": "2025-09-28T12:31:29.470Z",
      "source": "audit-follow-up"
    },
    {
      "id": 153,
      "title": "Resolve 150 open high-priority tickets",
      "description": "Resolve 150 open high-priority tickets\nThis ticket was generated automatically during the latest Opnix audit. Review spec/docs exports for full context.",
      "priority": "high",
      "status": "reported",
      "tags": [
        "FOLLOW_UP",
        "AUDIT"
      ],
      "modules": [],
      "created": "2025-09-28T12:31:29.470Z",
      "source": "audit-follow-up"
    }
  ],
  "nextId": 154
}